{"id":"ekv2okw34wowkjsfmxvrr6e4eqcnnyf5cvqimcouhi5kyqqyc24q","stamp":"2024-02-22T14:55:19.179648894Z","payload":{"op":"ballot_cancel","note":"","args":{"id":"pmp/motion/priority_poll/45"},"result":{"ad":{"community":{"git_repo":"https://github.com/pluralitybook/plurality-gov.public.git","git_branch":"main"},"id":"pmp/motion/priority_poll/45","owner":"motion:45+pmp-concern","purpose":"concern","motion_policy":"pmp-concern-policy","title":"Prioritization poll for motion 45","description":"Up/down vote the priority for concern (issue) 45","choices":["rank"],"policy":"qv","participants_group":"everybody","frozen":false,"closed":true,"cancelled":true,"parent_commit":"400177309739a4b27cce08598b17ea33b6fc91cb"},"outcome":{"summary":"cancelled","scores":{},"scores_by_user":{},"refunded":{}}}}}
