{"notices":[{"id":"ksynx5","stamp":"2024-09-06T18:13:51.765095647Z","notice":{"body":"Started managing this PR, using the Plural Management Protocol v1, as Gov4Git proposal `1002` with initial __approval score__ of `0.000000`.\n\nThis project is managed by [Gov4Git](https://gov4git.org), a decentralized governance system for collaborative git projects.\nTo participate in governance, __install the [Gov4Git desktop app](https://github.com/gov4git/desktop-application)__.\n\t"},"shown":true},{"id":"6qdu76","stamp":"2024-09-06T18:13:51.772038611Z","notice":{"body":"This PR's __approval score__ is now `0.000000`.\nThe __cost of review__ is `0.000000`.\nThe __projected bounty__ is now `0.000000`."},"shown":true},{"id":"sfdm6s","stamp":"2024-09-06T18:13:51.772040565Z","notice":{"body":"The set of eligible issues claimed by this PR is empty.\n"},"shown":true},{"id":"lwqbc4","stamp":"2024-10-08T14:32:45.12019269Z","notice":{"body":"This PR's __approval score__ is now `-20.000000`.\nThe __cost of review__ is `400.000000`.\nThe __projected bounty__ is now `0.000000`."},"shown":true},{"id":"3jc2kn","stamp":"2024-10-08T14:32:45.120194533Z","notice":{"body":"The set of eligible issues claimed by this PR is empty.\n"},"shown":true}]}
