{"community":{"git_repo":"https://github.com/pluralitybook/plurality-gov.public.git","git_branch":"main"},"id":"waimea/motion/priority_poll/159","owner":"motion:159+waimea-concern","purpose":"concern","motion_policy":"waimea-concern","title":"Prioritization poll for motion 159","description":"Vote for the priority of concern (issue) 159","choices":["rank"],"policy":"waimea-concern-approval","participants_group":"everybody","frozen":false,"closed":true,"cancelled":true,"parent_commit":"b51acd35f51df4ef43cce36268e96e3768e27612"}
