{"id":"b3sxgksuqwsn6sdug7r6zlnh7afqzvpzy7554733zwfnmbdzugia","stamp":"2024-03-19T18:20:56.91938964Z","payload":{"motion":{"open":null,"close":null,"cancel":{"id":"159","type":"concern","policy":"waimea-concern","receipts":[{"account":"user:shaudub","type":"refund","amount":{"asset":"plural","quantity":400}},{"account":"user:glenweyl","type":"refund","amount":{"asset":"plural","quantity":998001}},{"account":"user:jason-entenmann","type":"refund","amount":{"asset":"plural","quantity":25}},{"account":"user:lauerj","type":"refund","amount":{"asset":"plural","quantity":100}}]}}}}
